[{"annotations":[{"key":"illustrations","value":"no"},{"started_at":"Sat, 05 Dec 2015 10:53:04 GMT","finished_at":"Sat, 05 Dec 2015 10:53:10 GMT"},{"user_agent":"Mozilla/5.0 (Windows NT 6.3; WOW64; rv:42.0) Gecko/20100101 Firefox/42.0"},{"workflow":"untitled_workflow"}],"created_at":"2015-12-05T10:53:17.000Z","id":"5662c21d96ad6f0904001ab4","project_id":"54f42c0ab35d2e06bd000001","subject_id":"54f4bc9230017b04c901ec39","subject_ids":["54f4bc9230017b04c901ec39"],"subjects":[{"id":"54f4bc9230017b04c901ec39","zooniverse_id":"ASC0001z0o","location":{"standard":"http://zooniverse-static.s3.amazonaws.com/www.sciencegossip.org/subjects/standard/54f4bc9230017b04c901ec39.jpg","thumb":"http://zooniverse-static.s3.amazonaws.com/www.sciencegossip.org/subjects/thumb/54f4bc9230017b04c901ec39.jpg"}}],"tutorial":false,"updated_at":"2015-12-05T10:53:17.975Z","user_id":"5041cb2bba40af4d53000034","user_name":"elizabeth_s","workflow_id":"54f42c32b35d2e06bd000002"},{"annotations":[{"key":"illustrations","value":"yes"},{"key":"illustration","value":{"0":{"left":"110.152","top":"582.355","width":"606.745","height":"569.459","value":"drawing","frame":"0","details":{"keywords":"variolite; diabase; le chenaillet; ridge; chenaillet; spherulitic; thick"}}}},{"key":"parts"},{"key":"details","value":{"keywords":"variolite; diabase; le chenaillet; ridge; chenaillet; spherulitic; thick"}},{"key":"review","value":""},{"started_at":"Tue, 19 Jan 2016 17:45:26 GMT","finished_at":"Tue, 19 Jan 2016 17:46:01 GMT"},{"user_agent":"Mozilla/5.0 (Windows NT 6.1; WOW64) AppleWebKit/537.36 (KHTML, like Gecko) Chrome/47.0.2526.111 Safari/537.36"},{"workflow":"untitled_workflow"}],"created_at":"2016-01-19T17:46:01.000Z","id":"569e7659ff90383c9100012a","project_id":"54f42c0ab35d2e06bd000001","subject_id":"54f4bc9230017b04c901ec39","subject_ids":["54f4bc9230017b04c901ec39"],"subjects":[{"id":"54f4bc9230017b04c901ec39","zooniverse_id":"ASC0001z0o","location":{"standard":"http://zooniverse-static.s3.amazonaws.com/www.sciencegossip.org/subjects/standard/54f4bc9230017b04c901ec39.jpg","thumb":"http://zooniverse-static.s3.amazonaws.com/www.sciencegossip.org/subjects/thumb/54f4bc9230017b04c901ec39.jpg"}}],"tutorial":false,"updated_at":"2016-01-19T17:46:01.551Z","user_id":"5584930c2a19956404000bc4","user_name":"OneTwoTree","workflow_id":"54f42c32b35d2e06bd000002"},{"annotations":[{"key":"illustrations","value":"skip"},{"started_at":"Mon, 22 May 2017 15:25:56 GMT","finished_at":"Mon, 22 May 2017 15:26:00 GMT"},{"user_agent":"Mozilla/5.0 (Windows NT 6.1) AppleWebKit/537.36 (KHTML, like Gecko) Chrome/58.0.3029.110 Safari/537.36"},{"workflow":"untitled_workflow"}],"created_at":"2017-05-22T15:26:00.000Z","id":"5923030861ec3651d600401b","project_id":"54f42c0ab35d2e06bd000001","subject_id":"54f4bc9230017b04c901ec39","subject_ids":["54f4bc9230017b04c901ec39"],"subjects":[{"id":"54f4bc9230017b04c901ec39","zooniverse_id":"ASC0001z0o","location":{"standard":"http://zooniverse-static.s3.amazonaws.com/www.sciencegossip.org/subjects/standard/54f4bc9230017b04c901ec39.jpg","thumb":"http://zooniverse-static.s3.amazonaws.com/www.sciencegossip.org/subjects/thumb/54f4bc9230017b04c901ec39.jpg"}}],"tutorial":false,"updated_at":"2017-05-22T15:26:00.974Z","user_id":null,"workflow_id":"54f42c32b35d2e06bd000002"},{"annotations":[{"key":"illustrations","value":"yes"},{"key":"illustration","value":{"0":{"left":"127.513","top":"590.981","width":"590.27","height":"560.135","value":"drawing","frame":"0","parts":{"0":{"x":"153.652","y":"645.579","value":"inscription","frame":"0","inscription":{"text":"Variolite-diabase; north end of Le Chenaillet Ridge"}}},"details":{"keywords":"geology"}}}},{"key":"parts","value":{"0":{"x":"153.652","y":"645.579","value":"inscription","frame":"0","inscription":{"text":"Variolite-diabase; north end of Le Chenaillet Ridge"}}}},{"key":"details","value":{"keywords":"geology"}},{"key":"review","value":""},{"started_at":"Sat, 27 May 2017 15:03:02 GMT","finished_at":"Sat, 27 May 2017 15:04:17 GMT"},{"user_agent":"Mozilla/5.0 (X11; Linux i686) AppleWebKit/601.1 (KHTML, like Gecko) Version/8.0 Safari/601.1 Ubuntu/15.10 (3.16.3-1ubuntu1) Epiphany/3.16.3"},{"workflow":"untitled_workflow"}],"created_at":"2017-05-27T15:04:14.000Z","id":"5929956e61ec363bdd002cc5","project_id":"54f42c0ab35d2e06bd000001","subject_id":"54f4bc9230017b04c901ec39","subject_ids":["54f4bc9230017b04c901ec39"],"subjects":[{"id":"54f4bc9230017b04c901ec39","zooniverse_id":"ASC0001z0o","location":{"standard":"http://zooniverse-static.s3.amazonaws.com/www.sciencegossip.org/subjects/standard/54f4bc9230017b04c901ec39.jpg","thumb":"http://zooniverse-static.s3.amazonaws.com/www.sciencegossip.org/subjects/thumb/54f4bc9230017b04c901ec39.jpg"}}],"tutorial":false,"updated_at":"2017-05-27T15:04:14.903Z","user_id":"5040fb210454e2794000004f","user_name":"c196948","workflow_id":"54f42c32b35d2e06bd000002"},{"annotations":[{"key":"illustrations","value":"yes"},{"key":"illustration","value":{"0":{"left":"124.384","top":"639.617","width":"597.424","height":"421.643","value":"drawing","frame":"0","details":{"keywords":"variolite diabase, Le Chenaillet Ridge"}}}},{"key":"parts","value":{"0":{"x":"313.481","y":"626.3","value":"species","frame":"0","subject":{"common":"","scientific":"variolite diabase"}}}},{"key":"details","value":{"keywords":"variolite diabase, Le Chenaillet Ridge"}},{"key":"review","value":""},{"started_at":"Tue, 02 Jan 2018 07:34:02 GMT","finished_at":"Tue, 02 Jan 2018 07:35:50 GMT"},{"user_agent":"Mozilla/5.0 (Macintosh; Intel Mac OS X 10_13_2) AppleWebKit/537.36 (KHTML, like Gecko) Chrome/63.0.3239.84 Safari/537.36"},{"workflow":"untitled_workflow"}],"created_at":"2018-01-02T07:35:51.000Z","id":"5a4b3657b941906abd00018b","project_id":"54f42c0ab35d2e06bd000001","subject_id":"54f4bc9230017b04c901ec39","subject_ids":["54f4bc9230017b04c901ec39"],"subjects":[{"id":"54f4bc9230017b04c901ec39","zooniverse_id":"ASC0001z0o","location":{"standard":"http://zooniverse-static.s3.amazonaws.com/www.sciencegossip.org/subjects/standard/54f4bc9230017b04c901ec39.jpg","thumb":"http://zooniverse-static.s3.amazonaws.com/www.sciencegossip.org/subjects/thumb/54f4bc9230017b04c901ec39.jpg"}}],"tutorial":false,"updated_at":"2018-01-02T07:35:51.116Z","user_id":null,"workflow_id":"54f42c32b35d2e06bd000002"},{"annotations":[{"key":"illustrations","value":"yes"},{"key":"illustration"},{"key":"parts"},{"key":"details","value":{"keywords":""}},{"key":"review","value":""},{"started_at":"Wed, 24 Oct 2018 15:55:44 GMT","finished_at":"Wed, 24 Oct 2018 16:00:20 GMT"},{"user_agent":"Mozilla/5.0 (Windows NT 10.0; Win64; x64) AppleWebKit/537.36 (KHTML, like Gecko) Chrome/64.0.3282.140 Safari/537.36 Edge/17.17134"},{"workflow":"untitled_workflow"}],"created_at":"2018-10-24T16:00:18.000Z","id":"5bd09712338e15055900197f","project_id":"54f42c0ab35d2e06bd000001","subject_id":"54f4bc9230017b04c901ec39","subject_ids":["54f4bc9230017b04c901ec39"],"subjects":[{"id":"54f4bc9230017b04c901ec39","zooniverse_id":"ASC0001z0o","location":{"standard":"http://zooniverse-static.s3.amazonaws.com/www.sciencegossip.org/subjects/standard/54f4bc9230017b04c901ec39.jpg","thumb":"http://zooniverse-static.s3.amazonaws.com/www.sciencegossip.org/subjects/thumb/54f4bc9230017b04c901ec39.jpg"}}],"tutorial":false,"updated_at":"2018-10-24T16:00:19.725Z","user_id":null,"workflow_id":"54f42c32b35d2e06bd000002"},{"annotations":[{"key":"illustrations","value":"yes"},{"key":"illustration","value":{"0":{"left":"124.828","top":"599.653","width":"593.429","height":"552.147","value":"drawing","frame":"0","details":{"keywords":"Varioles, spherulites, variolite, "}}}},{"key":"parts"},{"key":"details","value":{"keywords":"Varioles, spherulites, variolite, "}},{"key":"review","value":""},{"started_at":"Wed, 28 Nov 2018 23:05:07 GMT","finished_at":"Thu, 29 Nov 2018 12:05:17 GMT"},{"user_agent":"Mozilla/5.0 (Windows NT 10.0; Win64; x64) AppleWebKit/537.36 (KHTML, like Gecko) Chrome/70.0.3538.102 Safari/537.36"},{"workflow":"untitled_workflow"}],"created_at":"2018-11-29T12:05:17.000Z","id":"5bffd5fd338e1500c200119c","project_id":"54f42c0ab35d2e06bd000001","subject_id":"54f4bc9230017b04c901ec39","subject_ids":["54f4bc9230017b04c901ec39"],"subjects":[{"id":"54f4bc9230017b04c901ec39","zooniverse_id":"ASC0001z0o","location":{"standard":"http://zooniverse-static.s3.amazonaws.com/www.sciencegossip.org/subjects/standard/54f4bc9230017b04c901ec39.jpg","thumb":"http://zooniverse-static.s3.amazonaws.com/www.sciencegossip.org/subjects/thumb/54f4bc9230017b04c901ec39.jpg"}}],"tutorial":false,"updated_at":"2018-11-29T12:05:18.033Z","user_id":"5bfb1d86338e15010c002bf0","user_name":"LydonPatascher644","workflow_id":"54f42c32b35d2e06bd000002"}]
