[{"annotations":[{"key":"illustrations","value":"yes"},{"key":"illustration","value":{"0":{"left":"66.338","top":"65.023","width":"711.375","height":"393.169","value":"drawing","frame":"0","details":{"keywords":"strawberry plants"}}}},{"key":"parts"},{"key":"details","value":{"keywords":"strawberry plants"}},{"key":"review","value":""},{"started_at":"Wed, 13 May 2015 17:44:21 GMT","finished_at":"Wed, 13 May 2015 17:45:20 GMT"},{"user_agent":"Mozilla/5.0 (X11; Ubuntu; Linux x86_64; rv:37.0) Gecko/20100101 Firefox/37.0"},{"workflow":"untitled_workflow"}],"created_at":"2015-05-13T17:45:16.000Z","id":"55538dac5135d07faf0000ff","project_id":"54f42c0ab35d2e06bd000001","subject_id":"5527af5ca092de04cc000e03","subject_ids":["5527af5ca092de04cc000e03"],"subjects":[{"id":"5527af5ca092de04cc000e03","zooniverse_id":"ASC0002mxn","location":{"standard":"http://zooniverse-static.s3.amazonaws.com/www.sciencegossip.org/subjects/standard/5527af5ca092de04cc000e03.jpg","thumb":"http://zooniverse-static.s3.amazonaws.com/www.sciencegossip.org/subjects/thumb/5527af5ca092de04cc000e03.jpg"}}],"tutorial":false,"updated_at":"2015-05-13T17:45:17.558Z","user_id":"504dff890454e25418000193","user_name":"jules","workflow_id":"54f42c32b35d2e06bd000002"},{"annotations":[{"key":"illustrations","value":"yes"},{"key":"illustration","value":{"0":{"left":"62.861","top":"73.231","width":"700.592","height":"383.732","value":"drawing","frame":"0","details":{"keywords":"strawberries; plant; garden; pot;"}}}},{"key":"parts"},{"key":"details","value":{"keywords":"strawberries; plant; garden; pot;"}},{"key":"review","value":""},{"started_at":"Wed, 20 May 2015 15:35:16 GMT","finished_at":"Wed, 20 May 2015 15:36:00 GMT"},{"user_agent":"Mozilla/5.0 (Windows NT 6.0) AppleWebKit/537.36 (KHTML, like Gecko) Chrome/42.0.2311.152 Safari/537.36"},{"workflow":"untitled_workflow"}],"created_at":"2015-05-20T15:35:54.000Z","id":"555ca9dab6021d7b8a001db7","project_id":"54f42c0ab35d2e06bd000001","subject_id":"5527af5ca092de04cc000e03","subject_ids":["5527af5ca092de04cc000e03"],"subjects":[{"id":"5527af5ca092de04cc000e03","zooniverse_id":"ASC0002mxn","location":{"standard":"http://zooniverse-static.s3.amazonaws.com/www.sciencegossip.org/subjects/standard/5527af5ca092de04cc000e03.jpg","thumb":"http://zooniverse-static.s3.amazonaws.com/www.sciencegossip.org/subjects/thumb/5527af5ca092de04cc000e03.jpg"}}],"tutorial":false,"updated_at":"2015-05-20T15:35:54.358Z","user_id":"555b638fb6021d4953000039","user_name":"heatherotis","workflow_id":"54f42c32b35d2e06bd000002"},{"annotations":[{"key":"illustrations","value":"yes"},{"key":"illustration","value":{"0":{"left":"414.095","top":"135.946","width":"0","height":"0","value":"drawing","frame":"0","details":{"keywords":"Strawberry"}}}},{"key":"parts","value":{"0":{"x":"443.735","y":"363.814","value":"species","frame":"0","subject":{"common":"strawberry","scientific":"Fragaria"}}}},{"key":"details","value":{"keywords":"Strawberry"}},{"key":"review","value":""},{"started_at":"Wed, 03 Jun 2015 10:51:05 GMT","finished_at":"Wed, 03 Jun 2015 10:53:36 GMT"},{"user_agent":"Mozilla/5.0 (X11; Ubuntu; Linux x86_64; rv:24.0) Gecko/20100101 Firefox/24.0"},{"workflow":"untitled_workflow"}],"created_at":"2015-06-03T10:52:59.000Z","id":"556edc8b5135d01925000ea3","project_id":"54f42c0ab35d2e06bd000001","subject_id":"5527af5ca092de04cc000e03","subject_ids":["5527af5ca092de04cc000e03"],"subjects":[{"id":"5527af5ca092de04cc000e03","zooniverse_id":"ASC0002mxn","location":{"standard":"http://zooniverse-static.s3.amazonaws.com/www.sciencegossip.org/subjects/standard/5527af5ca092de04cc000e03.jpg","thumb":"http://zooniverse-static.s3.amazonaws.com/www.sciencegossip.org/subjects/thumb/5527af5ca092de04cc000e03.jpg"}}],"tutorial":false,"updated_at":"2015-06-03T10:53:05.890Z","user_id":null,"workflow_id":"54f42c32b35d2e06bd000002"},{"annotations":[{"key":"illustrations","value":"yes"},{"key":"illustration","value":{"0":{"left":"54.225","top":"76.899","width":"691.156","height":"375.643","value":"drawing","frame":"0","details":{"keywords":"hirticulture; strawberry; propagator; design"}}}},{"key":"parts"},{"key":"details","value":{"keywords":"hirticulture; strawberry; propagator; design"}},{"key":"review","value":""},{"started_at":"Fri, 12 Jun 2015 12:35:44 GMT","finished_at":"Fri, 12 Jun 2015 12:36:46 GMT"},{"user_agent":"Mozilla/5.0 (Windows NT 6.1; WOW64) AppleWebKit/537.36 (KHTML, like Gecko) Chrome/38.0.2125.104 Safari/537.36"},{"workflow":"untitled_workflow"}],"created_at":"2015-06-12T12:36:49.000Z","id":"557ad2612a199537600013f1","project_id":"54f42c0ab35d2e06bd000001","subject_id":"5527af5ca092de04cc000e03","subject_ids":["5527af5ca092de04cc000e03"],"subjects":[{"id":"5527af5ca092de04cc000e03","zooniverse_id":"ASC0002mxn","location":{"standard":"http://zooniverse-static.s3.amazonaws.com/www.sciencegossip.org/subjects/standard/5527af5ca092de04cc000e03.jpg","thumb":"http://zooniverse-static.s3.amazonaws.com/www.sciencegossip.org/subjects/thumb/5527af5ca092de04cc000e03.jpg"}}],"tutorial":false,"updated_at":"2015-06-12T12:36:49.508Z","user_id":"50c8b03856175a0ab3000048","user_name":"brownfox","workflow_id":"54f42c32b35d2e06bd000002"},{"annotations":[{"key":"illustrations","value":"yes"},{"key":"illustration","value":{"0":{"left":"55.012","top":"81.855","width":"715.42","height":"378.337","value":"drawing","frame":"0","parts":{"0":{"x":"162.878","y":"157.362","value":"species","frame":"0","subject":{"common":"Strawberry","scientific":""}}},"details":{"keywords":"Strawberry plot; gardening; strawberry"}}}},{"key":"parts","value":{"0":{"x":"162.878","y":"157.362","value":"species","frame":"0","subject":{"common":"Strawberry","scientific":""}}}},{"key":"details","value":{"keywords":"Strawberry plot; gardening; strawberry"}},{"key":"review","value":""},{"started_at":"Fri, 12 Jun 2015 19:31:16 GMT","finished_at":"Fri, 12 Jun 2015 19:32:19 GMT"},{"user_agent":"Mozilla/5.0 (Windows NT 6.1; rv:38.0) Gecko/20100101 Firefox/38.0"},{"workflow":"untitled_workflow"}],"created_at":"2015-06-12T19:32:23.000Z","id":"557b33c72a199532340006c0","project_id":"54f42c0ab35d2e06bd000001","subject_id":"5527af5ca092de04cc000e03","subject_ids":["5527af5ca092de04cc000e03"],"subjects":[{"id":"5527af5ca092de04cc000e03","zooniverse_id":"ASC0002mxn","location":{"standard":"http://zooniverse-static.s3.amazonaws.com/www.sciencegossip.org/subjects/standard/5527af5ca092de04cc000e03.jpg","thumb":"http://zooniverse-static.s3.amazonaws.com/www.sciencegossip.org/subjects/thumb/5527af5ca092de04cc000e03.jpg"}}],"tutorial":false,"updated_at":"2015-06-12T19:32:23.155Z","user_id":"557744d76ee80c361f000852","user_name":"mturman","workflow_id":"54f42c32b35d2e06bd000002"}]
