[{"annotations":[{"key":"illustrations","value":"yes"},{"key":"illustration","value":{"0":{"left":"50.366","top":"256.904","width":"729.721","height":"919.133","value":"drawing","frame":"0","details":{"keywords":"garden design; suburban garden; garden paths; scale; position house vis-a-vis garden"}}}},{"key":"parts"},{"key":"details","value":{"keywords":"garden design; suburban garden; garden paths; scale; position house vis-a-vis garden"}},{"key":"review","value":""},{"started_at":"Wed, 14 Oct 2015 13:46:55 GMT","finished_at":"Wed, 14 Oct 2015 13:49:08 GMT"},{"user_agent":"Mozilla/5.0 (iPad; CPU OS 9_0_2 like Mac OS X) AppleWebKit/601.1.46 (KHTML, like Gecko) Version/9.0 Mobile/13A452 Safari/601.1"},{"workflow":"untitled_workflow"}],"created_at":"2015-10-14T13:49:09.000Z","id":"561e5d551dd53e638500301a","project_id":"54f42c0ab35d2e06bd000001","subject_id":"5527afd4a092de04cc004fb9","subject_ids":["5527afd4a092de04cc004fb9"],"subjects":[{"id":"5527afd4a092de04cc004fb9","zooniverse_id":"ASC0002tef","location":{"standard":"http://zooniverse-static.s3.amazonaws.com/www.sciencegossip.org/subjects/standard/5527afd4a092de04cc004fb9.jpg","thumb":"http://zooniverse-static.s3.amazonaws.com/www.sciencegossip.org/subjects/thumb/5527afd4a092de04cc004fb9.jpg"}}],"tutorial":false,"updated_at":"2015-10-14T13:49:09.114Z","user_id":"561e51831dd53e00b600b658","user_name":"graaggedaan","workflow_id":"54f42c32b35d2e06bd000002"},{"annotations":[{"key":"illustrations","value":"yes"},{"key":"illustration","value":{"0":{"left":"43.649","top":"285.115","width":"688.077","height":"896.296","value":"drawing","frame":"0","details":{"keywords":"Frontages, houses, graphic "}}}},{"key":"parts"},{"key":"details","value":{"keywords":"Frontages, houses, graphic "}},{"key":"review","value":""},{"started_at":"Wed, 14 Oct 2015 20:15:02 GMT","finished_at":"Wed, 14 Oct 2015 20:16:04 GMT"},{"user_agent":"Mozilla/5.0 (iPad; CPU OS 9_0_2 like Mac OS X) AppleWebKit/601.1.46 (KHTML, like Gecko) Version/9.0 Mobile/13A452 Safari/601.1"},{"workflow":"untitled_workflow"}],"created_at":"2015-10-14T20:16:04.000Z","id":"561eb8041dd53e2a9d00abf5","project_id":"54f42c0ab35d2e06bd000001","subject_id":"5527afd4a092de04cc004fb9","subject_ids":["5527afd4a092de04cc004fb9"],"subjects":[{"id":"5527afd4a092de04cc004fb9","zooniverse_id":"ASC0002tef","location":{"standard":"http://zooniverse-static.s3.amazonaws.com/www.sciencegossip.org/subjects/standard/5527afd4a092de04cc004fb9.jpg","thumb":"http://zooniverse-static.s3.amazonaws.com/www.sciencegossip.org/subjects/thumb/5527afd4a092de04cc004fb9.jpg"}}],"tutorial":false,"updated_at":"2015-10-14T20:16:04.049Z","user_id":null,"workflow_id":"54f42c32b35d2e06bd000002"},{"annotations":[{"key":"illustrations","value":"skip"},{"started_at":"Tue, 27 Oct 2015 20:02:41 GMT","finished_at":"Tue, 27 Oct 2015 20:02:47 GMT"},{"user_agent":"Mozilla/5.0 (Windows NT 6.3; WOW64; rv:41.0) Gecko/20100101 Firefox/41.0"},{"workflow":"untitled_workflow"}],"created_at":"2015-10-27T20:02:47.000Z","id":"562fd8675ecec60dbe001b2c","project_id":"54f42c0ab35d2e06bd000001","subject_id":"5527afd4a092de04cc004fb9","subject_ids":["5527afd4a092de04cc004fb9"],"subjects":[{"id":"5527afd4a092de04cc004fb9","zooniverse_id":"ASC0002tef","location":{"standard":"http://zooniverse-static.s3.amazonaws.com/www.sciencegossip.org/subjects/standard/5527afd4a092de04cc004fb9.jpg","thumb":"http://zooniverse-static.s3.amazonaws.com/www.sciencegossip.org/subjects/thumb/5527afd4a092de04cc004fb9.jpg"}}],"tutorial":false,"updated_at":"2015-10-27T20:02:48.041Z","user_id":"5041cb2bba40af4d53000034","user_name":"elizabeth","workflow_id":"54f42c32b35d2e06bd000002"},{"annotations":[{"key":"illustrations","value":"yes"},{"key":"illustration","value":{"0":{"left":"74.021","top":"291.018","width":"638.903","height":"882.863","value":"map","frame":"0","parts":{"0":{"x":"378.962","y":"305.265","value":"inscription","frame":"0","inscription":{"text":"5"}}},"details":{"keywords":"design; garden;"}}}},{"key":"parts","value":{"0":{"x":"378.962","y":"305.265","value":"inscription","frame":"0","inscription":{"text":"5"}}}},{"key":"details","value":{"keywords":"design; garden;"}},{"key":"review","value":""},{"started_at":"Thu, 29 Oct 2015 12:45:50 GMT","finished_at":"Thu, 29 Oct 2015 12:46:12 GMT"},{"user_agent":"Mozilla/5.0 (Windows NT 6.1) AppleWebKit/537.36 (KHTML, like Gecko) Chrome/46.0.2490.80 Safari/537.36"},{"workflow":"untitled_workflow"}],"created_at":"2015-10-29T12:46:12.000Z","id":"563215145ecec6236e007b38","project_id":"54f42c0ab35d2e06bd000001","subject_id":"5527afd4a092de04cc004fb9","subject_ids":["5527afd4a092de04cc004fb9"],"subjects":[{"id":"5527afd4a092de04cc004fb9","zooniverse_id":"ASC0002tef","location":{"standard":"http://zooniverse-static.s3.amazonaws.com/www.sciencegossip.org/subjects/standard/5527afd4a092de04cc004fb9.jpg","thumb":"http://zooniverse-static.s3.amazonaws.com/www.sciencegossip.org/subjects/thumb/5527afd4a092de04cc004fb9.jpg"}}],"tutorial":false,"updated_at":"2015-10-29T12:46:12.624Z","user_id":"51503a90bd43fc045100000d","user_name":"Hanibal94","workflow_id":"54f42c32b35d2e06bd000002"},{"annotations":[{"key":"illustrations","value":"yes"},{"key":"illustration","value":{"0":{"left":"64.429","top":"315.198","width":"632.187","height":"858.682","value":"drawing","frame":"0","details":{"keywords":"garden; "}}}},{"key":"parts"},{"key":"details","value":{"keywords":"garden; "}},{"key":"review","value":""},{"started_at":"Sat, 14 Nov 2015 23:11:14 GMT","finished_at":"Sat, 14 Nov 2015 23:12:36 GMT"},{"user_agent":"Mozilla/5.0 (Macintosh; Intel Mac OS X 10_11_0) AppleWebKit/537.36 (KHTML, like Gecko) Chrome/46.0.2490.86 Safari/537.36"},{"workflow":"untitled_workflow"}],"created_at":"2015-11-14T23:12:36.000Z","id":"5647bfe485563a797b000bee","project_id":"54f42c0ab35d2e06bd000001","subject_id":"5527afd4a092de04cc004fb9","subject_ids":["5527afd4a092de04cc004fb9"],"subjects":[{"id":"5527afd4a092de04cc004fb9","zooniverse_id":"ASC0002tef","location":{"standard":"http://zooniverse-static.s3.amazonaws.com/www.sciencegossip.org/subjects/standard/5527afd4a092de04cc004fb9.jpg","thumb":"http://zooniverse-static.s3.amazonaws.com/www.sciencegossip.org/subjects/thumb/5527afd4a092de04cc004fb9.jpg"}}],"tutorial":false,"updated_at":"2015-11-14T23:12:36.453Z","user_id":"519fd683a507e84068000006","user_name":"cheronetolivia","workflow_id":"54f42c32b35d2e06bd000002"},{"annotations":[{"key":"illustrations","value":"skip"},{"started_at":"Mon, 23 Nov 2015 23:26:37 GMT","finished_at":"Mon, 23 Nov 2015 23:26:39 GMT"},{"user_agent":"Mozilla/5.0 (Windows NT 6.1; WOW64) AppleWebKit/537.36 (KHTML, like Gecko) Chrome/46.0.2490.86 Safari/537.36"},{"workflow":"untitled_workflow"}],"created_at":"2015-11-23T23:26:39.000Z","id":"5653a0af0e1a97510c000999","project_id":"54f42c0ab35d2e06bd000001","subject_id":"5527afd4a092de04cc004fb9","subject_ids":["5527afd4a092de04cc004fb9"],"subjects":[{"id":"5527afd4a092de04cc004fb9","zooniverse_id":"ASC0002tef","location":{"standard":"http://zooniverse-static.s3.amazonaws.com/www.sciencegossip.org/subjects/standard/5527afd4a092de04cc004fb9.jpg","thumb":"http://zooniverse-static.s3.amazonaws.com/www.sciencegossip.org/subjects/thumb/5527afd4a092de04cc004fb9.jpg"}}],"tutorial":false,"updated_at":"2015-11-23T23:26:39.195Z","user_id":"533b8878699fda02d50008f0","user_name":"nanotech","workflow_id":"54f42c32b35d2e06bd000002"},{"annotations":[{"key":"illustrations","value":"yes"},{"key":"illustration","value":{"0":{"left":"56.012","top":"299.892","width":"633.53","height":"868.616","value":"drawing","frame":"0","details":{"keywords":""}}}},{"key":"parts"},{"key":"details","value":{"keywords":""}},{"key":"review","value":""},{"started_at":"Wed, 03 Feb 2016 02:37:28 GMT","finished_at":"Wed, 03 Feb 2016 02:37:48 GMT"},{"user_agent":"Mozilla/5.0 (Windows NT 10.0; WOW64) AppleWebKit/537.36 (KHTML, like Gecko) Chrome/48.0.2564.97 Safari/537.36"},{"workflow":"untitled_workflow"}],"created_at":"2016-02-03T02:37:50.000Z","id":"56b167fef724d7159c0004a5","project_id":"54f42c0ab35d2e06bd000001","subject_id":"5527afd4a092de04cc004fb9","subject_ids":["5527afd4a092de04cc004fb9"],"subjects":[{"id":"5527afd4a092de04cc004fb9","zooniverse_id":"ASC0002tef","location":{"standard":"http://zooniverse-static.s3.amazonaws.com/www.sciencegossip.org/subjects/standard/5527afd4a092de04cc004fb9.jpg","thumb":"http://zooniverse-static.s3.amazonaws.com/www.sciencegossip.org/subjects/thumb/5527afd4a092de04cc004fb9.jpg"}}],"tutorial":false,"updated_at":"2016-02-03T02:37:50.695Z","user_id":"56b1661ff724d71f66000486","user_name":"JamieNP","workflow_id":"54f42c32b35d2e06bd000002"}]
