[{"annotations":[{"key":"illustrations","value":"yes"},{"key":"illustration","value":{"0":{"left":"29.805","top":"362.583","width":"179.188","height":"836.656","value":"drawing","frame":"0","details":{"keywords":"pheasant; trachea;\r\nintestinal Worms;\r\nhydatids;"}},"1":{"left":"214.515","top":"490.272","width":"190.665","height":"536.182","value":"drawing","frame":"0"},"2":{"left":"294.192","top":"487.667","width":"0","height":"0","value":"drawing","frame":"0"},"3":{"left":"376.637","top":"753.71","width":"3.5","height":"3.5","value":"drawing","frame":"0"}}},{"key":"parts"},{"key":"details","value":{"keywords":"pheasant; trachea;\r\nintestinal Worms;\r\nhydatids;"}},{"key":"review","value":""},{"started_at":"Fri, 06 Mar 2015 06:44:21 GMT","finished_at":"Fri, 06 Mar 2015 07:10:28 GMT"},{"user_agent":"Mozilla/5.0 (Windows NT 6.1; WOW64; Trident/7.0; SLCC2; .NET CLR 2.0.50727; .NET CLR 3.5.30729; .NET CLR 3.0.30729; Media Center PC 6.0; NP08; .NET4.0C; .NET4.0E; NP08; MAAU; rv:11.0) like Gecko"},{"workflow":"untitled_workflow"}],"created_at":"2015-03-06T07:10:26.000Z","id":"54f952e28f165b6601000114","project_id":"54f42c0ab35d2e06bd000001","subject_id":"54f43b05efc50104c3006123","subject_ids":["54f43b05efc50104c3006123"],"subjects":[{"id":"54f43b05efc50104c3006123","zooniverse_id":"ASC0000f9i","location":{"standard":"http://zooniverse-static.s3.amazonaws.com/www.sciencegossip.org/subjects/standard/54f43b05efc50104c3006123.jpg","thumb":"http://zooniverse-static.s3.amazonaws.com/www.sciencegossip.org/subjects/thumb/54f43b05efc50104c3006123.jpg"}}],"tutorial":false,"updated_at":"2015-03-06T07:10:26.594Z","user_id":null,"workflow_id":"54f42c32b35d2e06bd000002"},{"annotations":[{"key":"illustrations","value":"yes"},{"key":"illustration"},{"key":"parts"},{"key":"details","value":{"keywords":"Pheasant trachea; hydatids; Taenia; worms"}},{"key":"review","value":""},{"started_at":"Fri, 06 Mar 2015 07:10:26 GMT","finished_at":"Fri, 06 Mar 2015 07:12:58 GMT"},{"user_agent":"Mozilla/5.0 (Windows NT 6.3; Win64; x64; Trident/7.0; .NET4.0E; .NET4.0C; .NET CLR 3.5.30729; .NET CLR 2.0.50727; .NET CLR 3.0.30729; HPNTDFJS; rv:11.0) like Gecko"},{"workflow":"untitled_workflow"}],"created_at":"2015-03-06T07:12:56.000Z","id":"54f953788f165b6b9a000060","project_id":"54f42c0ab35d2e06bd000001","subject_id":"54f43b05efc50104c3006123","subject_ids":["54f43b05efc50104c3006123"],"subjects":[{"id":"54f43b05efc50104c3006123","zooniverse_id":"ASC0000f9i","location":{"standard":"http://zooniverse-static.s3.amazonaws.com/www.sciencegossip.org/subjects/standard/54f43b05efc50104c3006123.jpg","thumb":"http://zooniverse-static.s3.amazonaws.com/www.sciencegossip.org/subjects/thumb/54f43b05efc50104c3006123.jpg"}}],"tutorial":false,"updated_at":"2015-03-06T07:12:56.511Z","user_id":"52ce5439061b250964000d69","user_name":"CandyDawn","workflow_id":"54f42c32b35d2e06bd000002"},{"annotations":[{"key":"illustrations","value":"yes"},{"key":"illustration","value":{"0":{"left":"25.934","top":"340.91","width":"390.15","height":"894.836","value":"drawing","frame":"0","parts":{"0":{"x":"168.384","y":"794.04","value":"species","frame":"0","subject":{"common":"intestinal worm","scientific":""}}},"details":{"keywords":"intestinal worm; hydatid; worm; trachea; sucker; taenia"}}}},{"key":"parts","value":{"0":{"x":"168.384","y":"794.04","value":"species","frame":"0","subject":{"common":"intestinal worm","scientific":""}}}},{"key":"details","value":{"keywords":"intestinal worm; hydatid; worm; trachea; sucker; taenia"}},{"key":"review","value":""},{"started_at":"Sat, 07 Mar 2015 01:04:20 GMT","finished_at":"Sat, 07 Mar 2015 01:16:10 GMT"},{"user_agent":"Mozilla/5.0 (Windows NT 5.1; rv:36.0) Gecko/20100101 Firefox/36.0"},{"workflow":"untitled_workflow"}],"created_at":"2015-03-07T01:16:01.000Z","id":"54fa5151cf04414e560000a3","project_id":"54f42c0ab35d2e06bd000001","subject_id":"54f43b05efc50104c3006123","subject_ids":["54f43b05efc50104c3006123"],"subjects":[{"id":"54f43b05efc50104c3006123","zooniverse_id":"ASC0000f9i","location":{"standard":"http://zooniverse-static.s3.amazonaws.com/www.sciencegossip.org/subjects/standard/54f43b05efc50104c3006123.jpg","thumb":"http://zooniverse-static.s3.amazonaws.com/www.sciencegossip.org/subjects/thumb/54f43b05efc50104c3006123.jpg"}}],"tutorial":false,"updated_at":"2015-03-07T01:16:04.837Z","user_id":"51f7e0320aab2a30ec000006","user_name":"nextlola","workflow_id":"54f42c32b35d2e06bd000002"},{"annotations":[{"key":"illustrations","value":"skip"},{"started_at":"Sun, 08 Mar 2015 00:41:52 GMT","finished_at":"Sun, 08 Mar 2015 02:19:50 GMT"},{"user_agent":"Mozilla/5.0 (Windows NT 5.1) AppleWebKit/537.36 (KHTML, like Gecko) Chrome/40.0.2214.115 Safari/537.36"},{"workflow":"untitled_workflow"}],"created_at":"2015-03-08T02:16:46.000Z","id":"54fbb10ecf04411658000076","project_id":"54f42c0ab35d2e06bd000001","subject_id":"54f43b05efc50104c3006123","subject_ids":["54f43b05efc50104c3006123"],"subjects":[{"id":"54f43b05efc50104c3006123","zooniverse_id":"ASC0000f9i","location":{"standard":"http://zooniverse-static.s3.amazonaws.com/www.sciencegossip.org/subjects/standard/54f43b05efc50104c3006123.jpg","thumb":"http://zooniverse-static.s3.amazonaws.com/www.sciencegossip.org/subjects/thumb/54f43b05efc50104c3006123.jpg"}}],"tutorial":false,"updated_at":"2015-03-08T02:16:44.934Z","user_id":null,"workflow_id":"54f42c32b35d2e06bd000002"},{"annotations":[{"key":"illustrations","value":"yes"},{"key":"illustration","value":{"0":{"left":"50.06","top":"346.088","width":"710.323","height":"862.276","value":"drawing","frame":"0","details":{"keywords":"worm; hydatid; taenia; parasite; trachea"}}}},{"key":"parts"},{"key":"details","value":{"keywords":"worm; hydatid; taenia; parasite; trachea"}},{"key":"review","value":""},{"started_at":"Sun, 08 Mar 2015 20:50:50 GMT","finished_at":"Sun, 08 Mar 2015 20:54:04 GMT"},{"user_agent":"Mozilla/5.0 (Windows NT 6.3; WOW64; rv:36.0) Gecko/20100101 Firefox/36.0"},{"workflow":"untitled_workflow"}],"created_at":"2015-03-08T20:53:58.000Z","id":"54fcb6e68f165b4cd400504c","project_id":"54f42c0ab35d2e06bd000001","subject_id":"54f43b05efc50104c3006123","subject_ids":["54f43b05efc50104c3006123"],"subjects":[{"id":"54f43b05efc50104c3006123","zooniverse_id":"ASC0000f9i","location":{"standard":"http://zooniverse-static.s3.amazonaws.com/www.sciencegossip.org/subjects/standard/54f43b05efc50104c3006123.jpg","thumb":"http://zooniverse-static.s3.amazonaws.com/www.sciencegossip.org/subjects/thumb/54f43b05efc50104c3006123.jpg"}}],"tutorial":false,"updated_at":"2015-03-08T20:54:02.518Z","user_id":null,"workflow_id":"54f42c32b35d2e06bd000002"},{"annotations":[{"key":"illustrations","value":"yes"},{"key":"illustration","value":{"0":{"left":"51.417","top":"343.623","width":"683.19","height":"860.919","value":"drawing","frame":"0","parts":{"0":{"x":"140.957","y":"1026.032","value":"contributor","frame":"0","name":{"name":"D. N. Worksop"},"role":{"role":"illustrator"}},"1":{"x":"108.397","y":"703.142","value":"species","frame":"0","subject":{"common":"","scientific":"Hydatid"}}},"details":{"keywords":"Hydatid; worm; intestinal; trachea; pheasant; head; parasite; sucker; length; lung;"}}}},{"key":"parts","value":{"0":{"x":"140.957","y":"1026.032","value":"contributor","frame":"0","name":{"name":"D. N. Worksop"},"role":{"role":"illustrator"}},"1":{"x":"108.397","y":"703.142","value":"species","frame":"0","subject":{"common":"","scientific":"Hydatid"}}}},{"key":"details","value":{"keywords":"Hydatid; worm; intestinal; trachea; pheasant; head; parasite; sucker; length; lung;"}},{"key":"review","value":""},{"started_at":"Mon, 09 Mar 2015 21:01:52 GMT","finished_at":"Mon, 09 Mar 2015 21:15:03 GMT"},{"user_agent":"Mozilla/5.0 (Windows NT 6.1; WOW64; rv:36.0) Gecko/20100101 Firefox/36.0"},{"workflow":"untitled_workflow"}],"created_at":"2015-03-09T21:15:00.000Z","id":"54fe0d54cf044177a700006d","project_id":"54f42c0ab35d2e06bd000001","subject_id":"54f43b05efc50104c3006123","subject_ids":["54f43b05efc50104c3006123"],"subjects":[{"id":"54f43b05efc50104c3006123","zooniverse_id":"ASC0000f9i","location":{"standard":"http://zooniverse-static.s3.amazonaws.com/www.sciencegossip.org/subjects/standard/54f43b05efc50104c3006123.jpg","thumb":"http://zooniverse-static.s3.amazonaws.com/www.sciencegossip.org/subjects/thumb/54f43b05efc50104c3006123.jpg"}}],"tutorial":false,"updated_at":"2015-03-09T21:15:02.822Z","user_id":"5050e7390454e2538d000bd8","user_name":"Antihelios","workflow_id":"54f42c32b35d2e06bd000002"},{"annotations":[{"key":"illustrations","value":"yes"},{"key":"illustration"},{"key":"parts"},{"key":"details","value":{"keywords":"D.N.Worksop;"}},{"key":"review","value":""},{"started_at":"Tue, 10 Mar 2015 22:54:22 GMT","finished_at":"Tue, 10 Mar 2015 23:00:16 GMT"},{"user_agent":"Mozilla/5.0 (Windows NT 6.1; WOW64) AppleWebKit/537.36 (KHTML, like Gecko) Chrome/40.0.2214.115 Safari/537.36"},{"workflow":"untitled_workflow"}],"created_at":"2015-03-10T23:00:13.000Z","id":"54ff777d0890a96fdc00041c","project_id":"54f42c0ab35d2e06bd000001","subject_id":"54f43b05efc50104c3006123","subject_ids":["54f43b05efc50104c3006123"],"subjects":[{"id":"54f43b05efc50104c3006123","zooniverse_id":"ASC0000f9i","location":{"standard":"http://zooniverse-static.s3.amazonaws.com/www.sciencegossip.org/subjects/standard/54f43b05efc50104c3006123.jpg","thumb":"http://zooniverse-static.s3.amazonaws.com/www.sciencegossip.org/subjects/thumb/54f43b05efc50104c3006123.jpg"}}],"tutorial":false,"updated_at":"2015-03-10T23:00:13.202Z","user_id":"52fe7b65f490b236c30011a1","user_name":"bobk47","workflow_id":"54f42c32b35d2e06bd000002"},{"annotations":[{"key":"illustrations","value":"yes"},{"key":"illustration","value":{"0":{"left":"12.334","top":"340.015","width":"208.357","height":"870.412","value":"drawing","frame":"0","details":{"keywords":"plant"}},"1":{"left":"216.405","top":"480.322","width":"203.717","height":"557.808","value":"drawing","frame":"0","details":{"keywords":"plant cross section"}}}},{"key":"parts"},{"key":"details","value":{"keywords":"plant"}},{"key":"details","value":{"keywords":"plant cross section"}},{"key":"review","value":""},{"started_at":"Fri, 13 Mar 2015 00:53:29 GMT","finished_at":"Fri, 13 Mar 2015 00:54:22 GMT"},{"user_agent":"Mozilla/5.0 (Macintosh; Intel Mac OS X 10_10_0) AppleWebKit/537.36 (KHTML, like Gecko) Chrome/41.0.2272.76 Safari/537.36"},{"workflow":"untitled_workflow"}],"created_at":"2015-03-13T00:54:19.000Z","id":"5502353b7037204b380007bc","project_id":"54f42c0ab35d2e06bd000001","subject_id":"54f43b05efc50104c3006123","subject_ids":["54f43b05efc50104c3006123"],"subjects":[{"id":"54f43b05efc50104c3006123","zooniverse_id":"ASC0000f9i","location":{"standard":"http://zooniverse-static.s3.amazonaws.com/www.sciencegossip.org/subjects/standard/54f43b05efc50104c3006123.jpg","thumb":"http://zooniverse-static.s3.amazonaws.com/www.sciencegossip.org/subjects/thumb/54f43b05efc50104c3006123.jpg"}}],"tutorial":false,"updated_at":"2015-03-13T00:54:19.878Z","user_id":"5501ee6270372061770003ca","user_name":"ronimorgan","workflow_id":"54f42c32b35d2e06bd000002"},{"annotations":[{"key":"illustrations","value":"yes"},{"key":"illustration","value":{"0":{"left":"35.544","top":"352.442","width":"752.38","height":"856.849","value":"drawing","frame":"0","parts":{"0":{"x":"172.568","y":"591.217","value":"species","frame":"0","subject":{"common":"Pheasant","scientific":""}},"1":{"x":"167.141","y":"792.005","value":"species","frame":"0","subject":{"common":"Worm","scientific":""}}},"details":{"keywords":"Pheasant; worms; parasite; hydatid"}}}},{"key":"parts","value":{"0":{"x":"172.568","y":"591.217","value":"species","frame":"0","subject":{"common":"Pheasant","scientific":""}},"1":{"x":"167.141","y":"792.005","value":"species","frame":"0","subject":{"common":"Worm","scientific":""}}}},{"key":"details","value":{"keywords":"Pheasant; worms; parasite; hydatid"}},{"key":"review","value":""},{"started_at":"Thu, 19 Mar 2015 15:48:01 GMT","finished_at":"Thu, 19 Mar 2015 15:52:21 GMT"},{"user_agent":"Mozilla/5.0 (Macintosh; Intel Mac OS X 10.9; rv:35.0) Gecko/20100101 Firefox/35.0"},{"workflow":"untitled_workflow"}],"created_at":"2015-03-19T15:52:27.000Z","id":"550af0bb051370651e0004c2","project_id":"54f42c0ab35d2e06bd000001","subject_id":"54f43b05efc50104c3006123","subject_ids":["54f43b05efc50104c3006123"],"subjects":[{"id":"54f43b05efc50104c3006123","zooniverse_id":"ASC0000f9i","location":{"standard":"http://zooniverse-static.s3.amazonaws.com/www.sciencegossip.org/subjects/standard/54f43b05efc50104c3006123.jpg","thumb":"http://zooniverse-static.s3.amazonaws.com/www.sciencegossip.org/subjects/thumb/54f43b05efc50104c3006123.jpg"}}],"tutorial":false,"updated_at":"2015-03-19T15:52:26.782Z","user_id":null,"workflow_id":"54f42c32b35d2e06bd000002"},{"annotations":[{"key":"illustrations","value":"yes"},{"key":"illustration","value":{"0":{"left":"209.685","top":"492.532","width":"205.074","height":"528.531","value":"drawing","frame":"0","details":{"keywords":"worm"}},"1":{"left":"36.818","top":"352.225","width":"160.873","height":"848.706","value":"drawing","frame":"0","details":{"keywords":"worm"}}}},{"key":"parts"},{"key":"details","value":{"keywords":"worm"}},{"key":"details","value":{"keywords":"worm"}},{"key":"review","value":""},{"started_at":"Tue, 14 Apr 2015 16:37:23 GMT","finished_at":"Tue, 14 Apr 2015 16:40:58 GMT"},{"user_agent":"Mozilla/5.0 (Macintosh; Intel Mac OS X 10_9_5) AppleWebKit/537.36 (KHTML, like Gecko) Chrome/41.0.2272.118 Safari/537.36"},{"workflow":"untitled_workflow"}],"created_at":"2015-04-14T16:33:07.000Z","id":"552d414390ecf549090003de","project_id":"54f42c0ab35d2e06bd000001","subject_id":"54f43b05efc50104c3006123","subject_ids":["54f43b05efc50104c3006123"],"subjects":[{"id":"54f43b05efc50104c3006123","zooniverse_id":"ASC0000f9i","location":{"standard":"http://zooniverse-static.s3.amazonaws.com/www.sciencegossip.org/subjects/standard/54f43b05efc50104c3006123.jpg","thumb":"http://zooniverse-static.s3.amazonaws.com/www.sciencegossip.org/subjects/thumb/54f43b05efc50104c3006123.jpg"}}],"tutorial":false,"updated_at":"2015-04-14T16:33:20.741Z","user_id":null,"workflow_id":"54f42c32b35d2e06bd000002"},{"annotations":[{"key":"illustrations","value":"yes"},{"key":"illustration","value":{"0":{"left":"36.765","top":"350.728","width":"706.253","height":"860.349","value":"drawing","frame":"0","parts":{"0":{"x":"107.312","y":"521.099","value":"species","frame":"0","subject":{"common":"worm","scientific":"hydatid"}},"1":{"x":"310.812","y":"616.066","value":"species","frame":"0","subject":{"common":"worm","scientific":"hydatid"}},"2":{"x":"150.725","y":"564.513","value":"species","frame":"0","subject":{"common":"pheasant","scientific":""}}},"details":{"keywords":"pheasent; intestinal worm; hydatid; tapeworm; trachea; lungs; tubercles"}}}},{"key":"parts","value":{"0":{"x":"107.312","y":"521.099","value":"species","frame":"0","subject":{"common":"worm","scientific":"hydatid"}},"1":{"x":"310.812","y":"616.066","value":"species","frame":"0","subject":{"common":"worm","scientific":"hydatid"}},"2":{"x":"150.725","y":"564.513","value":"species","frame":"0","subject":{"common":"pheasant","scientific":""}}}},{"key":"details","value":{"keywords":"pheasent; intestinal worm; hydatid; tapeworm; trachea; lungs; tubercles"}},{"key":"review","value":""},{"started_at":"Wed, 15 Apr 2015 16:44:03 GMT","finished_at":"Wed, 15 Apr 2015 16:48:45 GMT"},{"user_agent":"Mozilla/5.0 (Windows NT 6.1; WOW64; rv:37.0) Gecko/20100101 Firefox/37.0"},{"workflow":"untitled_workflow"}],"created_at":"2015-04-15T16:50:18.000Z","id":"552e96ca40ead566a70007ae","project_id":"54f42c0ab35d2e06bd000001","subject_id":"54f43b05efc50104c3006123","subject_ids":["54f43b05efc50104c3006123"],"subjects":[{"id":"54f43b05efc50104c3006123","zooniverse_id":"ASC0000f9i","location":{"standard":"http://zooniverse-static.s3.amazonaws.com/www.sciencegossip.org/subjects/standard/54f43b05efc50104c3006123.jpg","thumb":"http://zooniverse-static.s3.amazonaws.com/www.sciencegossip.org/subjects/thumb/54f43b05efc50104c3006123.jpg"}}],"tutorial":false,"updated_at":"2015-04-15T16:50:18.947Z","user_id":null,"workflow_id":"54f42c32b35d2e06bd000002"}]
