[{"annotations":[{"key":"illustrations","value":"yes"},{"key":"illustration","value":{"0":{"left":"339.558","top":"140.306","width":"418.002","height":"344.773","value":"drawing","frame":"0","parts":{"0":{"x":"463.909","y":"163.149","value":"inscription","frame":"0","inscription":{"text":"5"}}},"details":{"keywords":"bird;"}}}},{"key":"parts","value":{"0":{"x":"463.909","y":"163.149","value":"inscription","frame":"0","inscription":{"text":"5"}}}},{"key":"details","value":{"keywords":"bird;"}},{"key":"review","value":""},{"started_at":"Wed, 04 Mar 2015 23:40:00 GMT","finished_at":"Wed, 04 Mar 2015 23:40:50 GMT"},{"user_agent":"Mozilla/5.0 (Macintosh; Intel Mac OS X 10_10_1) AppleWebKit/537.36 (KHTML, like Gecko) Chrome/40.0.2214.115 Safari/537.36"},{"workflow":"untitled_workflow"}],"created_at":"2015-03-04T23:40:48.000Z","id":"54f79800cf04410fc0000a6c","project_id":"54f42c0ab35d2e06bd000001","subject_id":"54f43ae9efc50104c3005657","subject_ids":["54f43ae9efc50104c3005657"],"subjects":[{"id":"54f43ae9efc50104c3005657","zooniverse_id":"ASC0000gfs","location":{"standard":"http://zooniverse-static.s3.amazonaws.com/www.sciencegossip.org/subjects/standard/54f43ae9efc50104c3005657.jpg","thumb":"http://zooniverse-static.s3.amazonaws.com/www.sciencegossip.org/subjects/thumb/54f43ae9efc50104c3005657.jpg"}}],"tutorial":false,"updated_at":"2015-03-04T23:40:48.427Z","user_id":null,"workflow_id":"54f42c32b35d2e06bd000002"},{"annotations":[{"key":"illustrations","value":"yes"},{"key":"illustration","value":{"0":{"left":"346.66","top":"143.38","width":"401.42","height":"332.332","value":"drawing","frame":"0","details":{"keywords":"bird; wood; "}}}},{"key":"parts"},{"key":"details","value":{"keywords":"bird; wood; "}},{"key":"review","value":""},{"started_at":"Fri, 06 Mar 2015 12:30:46 GMT","finished_at":"Fri, 06 Mar 2015 12:32:51 GMT"},{"user_agent":"Mozilla/5.0 (Windows NT 6.1; WOW64; rv:35.0) Gecko/20100101 Firefox/35.0"},{"workflow":"untitled_workflow"}],"created_at":"2015-03-06T12:32:47.000Z","id":"54f99e6fcf04413c3d0001fa","project_id":"54f42c0ab35d2e06bd000001","subject_id":"54f43ae9efc50104c3005657","subject_ids":["54f43ae9efc50104c3005657"],"subjects":[{"id":"54f43ae9efc50104c3005657","zooniverse_id":"ASC0000gfs","location":{"standard":"http://zooniverse-static.s3.amazonaws.com/www.sciencegossip.org/subjects/standard/54f43ae9efc50104c3005657.jpg","thumb":"http://zooniverse-static.s3.amazonaws.com/www.sciencegossip.org/subjects/thumb/54f43ae9efc50104c3005657.jpg"}}],"tutorial":false,"updated_at":"2015-03-06T12:32:48.058Z","user_id":"54e74e016975264827000782","user_name":"Aurelide","workflow_id":"54f42c32b35d2e06bd000002"},{"annotations":[{"key":"illustrations","value":"yes"},{"key":"illustration","value":{"0":{"left":"342.908","top":"138.566","width":"418.738","height":"332.337","value":"drawing","frame":"0","details":{"keywords":"bird; owl"}}}},{"key":"parts","value":{"0":{"x":"497.01","y":"44.612","value":"species","frame":"0","subject":{"common":"Fern Owl","scientific":"caprimidgus europaeus"}}}},{"key":"details","value":{"keywords":"bird; owl"}},{"key":"review","value":""},{"started_at":"Fri, 06 Mar 2015 14:49:38 GMT","finished_at":"Fri, 06 Mar 2015 14:51:15 GMT"},{"user_agent":"Mozilla/5.0 (Windows NT 6.3; WOW64) AppleWebKit/537.36 (KHTML, like Gecko) Chrome/40.0.2214.115 Safari/537.36"},{"workflow":"untitled_workflow"}],"created_at":"2015-03-06T14:51:09.000Z","id":"54f9bedd8f165b52490009df","project_id":"54f42c0ab35d2e06bd000001","subject_id":"54f43ae9efc50104c3005657","subject_ids":["54f43ae9efc50104c3005657"],"subjects":[{"id":"54f43ae9efc50104c3005657","zooniverse_id":"ASC0000gfs","location":{"standard":"http://zooniverse-static.s3.amazonaws.com/www.sciencegossip.org/subjects/standard/54f43ae9efc50104c3005657.jpg","thumb":"http://zooniverse-static.s3.amazonaws.com/www.sciencegossip.org/subjects/thumb/54f43ae9efc50104c3005657.jpg"}}],"tutorial":false,"updated_at":"2015-03-06T14:51:10.201Z","user_id":"526f9659fe16d978510003c8","user_name":"crmoorhead","workflow_id":"54f42c32b35d2e06bd000002"},{"annotations":[{"key":"illustrations","value":"yes"},{"key":"illustration"},{"key":"parts"},{"key":"details","value":{"keywords":"Caprimulgus europaeus \r\nor fern owl"}},{"key":"review","value":""},{"started_at":"Fri, 06 Mar 2015 19:21:49 GMT","finished_at":"Fri, 06 Mar 2015 19:24:48 GMT"},{"user_agent":"Mozilla/5.0 (Macintosh; Intel Mac OS X 10_9_5) AppleWebKit/600.3.18 (KHTML, like Gecko) Version/7.1.3 Safari/537.85.12"},{"workflow":"untitled_workflow"}],"created_at":"2015-03-06T19:24:46.000Z","id":"54f9fefecf04415a9b000215","project_id":"54f42c0ab35d2e06bd000001","subject_id":"54f43ae9efc50104c3005657","subject_ids":["54f43ae9efc50104c3005657"],"subjects":[{"id":"54f43ae9efc50104c3005657","zooniverse_id":"ASC0000gfs","location":{"standard":"http://zooniverse-static.s3.amazonaws.com/www.sciencegossip.org/subjects/standard/54f43ae9efc50104c3005657.jpg","thumb":"http://zooniverse-static.s3.amazonaws.com/www.sciencegossip.org/subjects/thumb/54f43ae9efc50104c3005657.jpg"}}],"tutorial":false,"updated_at":"2015-03-06T19:24:46.206Z","user_id":"54e935df6975264a6a0002f4","user_name":"davidmask","workflow_id":"54f42c32b35d2e06bd000002"},{"annotations":[{"key":"illustrations","value":"yes"},{"key":"illustration","value":{"0":{"left":"363.976","top":"182.779","width":"434.028","height":"295.769","value":"drawing","frame":"0","parts":{"0":{"x":"539.345","y":"347.198","value":"species","frame":"0","subject":{"common":"Fern Owl","scientific":""}}},"details":{"keywords":"Fern owl with enlarged diagram of foot"}}}},{"key":"parts","value":{"0":{"x":"832.454","y":"121.986","value":"species","frame":"0"},"1":{"x":"539.345","y":"347.198","value":"species","frame":"0","subject":{"common":"Fern Owl","scientific":""}}}},{"key":"details","value":{"keywords":"Fern owl with enlarged diagram of foot"}},{"key":"review","value":""},{"started_at":"Fri, 06 Mar 2015 19:53:13 GMT","finished_at":"Fri, 06 Mar 2015 19:55:49 GMT"},{"user_agent":"Mozilla/5.0 (iPad; CPU OS 8_1_3 like Mac OS X) AppleWebKit/600.1.4 (KHTML, like Gecko) Version/8.0 Mobile/12B466 Safari/600.1.4"},{"workflow":"untitled_workflow"}],"created_at":"2015-03-06T19:55:45.000Z","id":"54fa0641cf04415f1a0003e6","project_id":"54f42c0ab35d2e06bd000001","subject_id":"54f43ae9efc50104c3005657","subject_ids":["54f43ae9efc50104c3005657"],"subjects":[{"id":"54f43ae9efc50104c3005657","zooniverse_id":"ASC0000gfs","location":{"standard":"http://zooniverse-static.s3.amazonaws.com/www.sciencegossip.org/subjects/standard/54f43ae9efc50104c3005657.jpg","thumb":"http://zooniverse-static.s3.amazonaws.com/www.sciencegossip.org/subjects/thumb/54f43ae9efc50104c3005657.jpg"}}],"tutorial":false,"updated_at":"2015-03-06T19:55:48.672Z","user_id":"52cf0c246d91313d3000016b","user_name":"Helenmaxwell","workflow_id":"54f42c32b35d2e06bd000002"},{"annotations":[{"key":"illustrations","value":"yes"},{"key":"illustration","value":{"0":{"left":"349.171","top":"144.093","width":"401.421","height":"348.917","value":"drawing","frame":"0","details":{"keywords":"Fern Owl; caprimulgus europae"}}}},{"key":"parts"},{"key":"details","value":{"keywords":"Fern Owl; caprimulgus europae"}},{"key":"review","value":""},{"started_at":"Sat, 07 Mar 2015 00:47:51 GMT","finished_at":"Sat, 07 Mar 2015 00:48:42 GMT"},{"user_agent":"Mozilla/5.0 (Windows NT 6.3; WOW64) AppleWebKit/537.36 (KHTML, like Gecko) Chrome/40.0.2214.115 Safari/537.36"},{"workflow":"untitled_workflow"}],"created_at":"2015-03-07T00:48:38.000Z","id":"54fa4ae68f165b4d2e0001e5","project_id":"54f42c0ab35d2e06bd000001","subject_id":"54f43ae9efc50104c3005657","subject_ids":["54f43ae9efc50104c3005657"],"subjects":[{"id":"54f43ae9efc50104c3005657","zooniverse_id":"ASC0000gfs","location":{"standard":"http://zooniverse-static.s3.amazonaws.com/www.sciencegossip.org/subjects/standard/54f43ae9efc50104c3005657.jpg","thumb":"http://zooniverse-static.s3.amazonaws.com/www.sciencegossip.org/subjects/thumb/54f43ae9efc50104c3005657.jpg"}}],"tutorial":false,"updated_at":"2015-03-07T00:48:39.444Z","user_id":"54fa4987cf044143e400016a","user_name":"gamorin","workflow_id":"54f42c32b35d2e06bd000002"},{"annotations":[{"key":"illustrations","value":"yes"},{"key":"illustration","value":{"0":{"left":"338.118","top":"142.711","width":"429.054","height":"336.482","value":"drawing","frame":"0","details":{"keywords":"fern owl; european nightjar"}}}},{"key":"parts","value":{"0":{"x":"821.703","y":"402.465","value":"species","frame":"0"},"1":{"x":"794.069","y":"391.412","value":"species","frame":"0","subject":{"common":"Fern Owl","scientific":"Caprimulgus europaeus"}}}},{"key":"details","value":{"keywords":"fern owl; european nightjar"}},{"key":"review","value":""},{"started_at":"Sat, 07 Mar 2015 20:23:23 GMT","finished_at":"Sat, 07 Mar 2015 20:26:24 GMT"},{"user_agent":"Mozilla/5.0 (Windows NT 6.1; WOW64) AppleWebKit/537.36 (KHTML, like Gecko) Chrome/40.0.2214.115 Safari/537.36"},{"workflow":"untitled_workflow"}],"created_at":"2015-03-07T20:26:19.000Z","id":"54fb5eebcf04414828001a3c","project_id":"54f42c0ab35d2e06bd000001","subject_id":"54f43ae9efc50104c3005657","subject_ids":["54f43ae9efc50104c3005657"],"subjects":[{"id":"54f43ae9efc50104c3005657","zooniverse_id":"ASC0000gfs","location":{"standard":"http://zooniverse-static.s3.amazonaws.com/www.sciencegossip.org/subjects/standard/54f43ae9efc50104c3005657.jpg","thumb":"http://zooniverse-static.s3.amazonaws.com/www.sciencegossip.org/subjects/thumb/54f43ae9efc50104c3005657.jpg"}}],"tutorial":false,"updated_at":"2015-03-07T20:26:19.542Z","user_id":"5409f1a6845bdc2766000563","user_name":"BlindOracle","workflow_id":"54f42c32b35d2e06bd000002"},{"annotations":[{"key":"illustrations","value":"yes"},{"key":"illustration","value":{"0":{"left":"352.922","top":"149.619","width":"400.867","height":"330.311","value":"drawing","frame":"0","details":{"keywords":""}}}},{"key":"parts"},{"key":"details","value":{"keywords":""}},{"key":"review","value":""},{"started_at":"Sun, 08 Mar 2015 15:09:07 GMT","finished_at":"Sun, 08 Mar 2015 15:11:18 GMT"},{"user_agent":"Mozilla/5.0 (iPad; CPU OS 8_1_3 like Mac OS X) AppleWebKit/600.1.4 (KHTML, like Gecko) CriOS/40.0.2214.73 Mobile/12B466 Safari/600.1.4 (000841)"},{"workflow":"untitled_workflow"}],"created_at":"2015-03-08T15:11:12.000Z","id":"54fc6690cf04411eb3000134","project_id":"54f42c0ab35d2e06bd000001","subject_id":"54f43ae9efc50104c3005657","subject_ids":["54f43ae9efc50104c3005657"],"subjects":[{"id":"54f43ae9efc50104c3005657","zooniverse_id":"ASC0000gfs","location":{"standard":"http://zooniverse-static.s3.amazonaws.com/www.sciencegossip.org/subjects/standard/54f43ae9efc50104c3005657.jpg","thumb":"http://zooniverse-static.s3.amazonaws.com/www.sciencegossip.org/subjects/thumb/54f43ae9efc50104c3005657.jpg"}}],"tutorial":false,"updated_at":"2015-03-08T15:11:15.495Z","user_id":null,"workflow_id":"54f42c32b35d2e06bd000002"},{"annotations":[{"key":"illustrations","value":"yes"},{"key":"illustration","value":{"0":{"left":"345.198","top":"132.585","width":"441.048","height":"345.688","value":"drawing","frame":"0","parts":{"0":{"x":"457.232","y":"169.99","value":"inscription","frame":"0","inscription":{"text":"5"}},"1":{"x":"701.852","y":"280.552","value":"species","frame":"0","subject":{"common":"?Caprimidgus europaeud","scientific":"?  Fern owl"}}},"details":{"keywords":"Fern owl"}}}},{"key":"parts","value":{"0":{"x":"457.232","y":"169.99","value":"inscription","frame":"0","inscription":{"text":"5"}},"1":{"x":"701.852","y":"280.552","value":"species","frame":"0","subject":{"common":"?Caprimidgus europaeud","scientific":"?  Fern owl"}}}},{"key":"details","value":{"keywords":"Fern owl"}},{"key":"review","value":""},{"started_at":"Sun, 08 Mar 2015 21:45:27 GMT","finished_at":"Sun, 08 Mar 2015 21:48:29 GMT"},{"user_agent":"Mozilla/5.0 (iPad; CPU OS 7_1_2 like Mac OS X) AppleWebKit/537.51.2 (KHTML, like Gecko) Version/7.0 Mobile/11D257 Safari/9537.53"},{"workflow":"untitled_workflow"}],"created_at":"2015-03-08T21:48:23.000Z","id":"54fcc3a7cf044148280054ae","project_id":"54f42c0ab35d2e06bd000001","subject_id":"54f43ae9efc50104c3005657","subject_ids":["54f43ae9efc50104c3005657"],"subjects":[{"id":"54f43ae9efc50104c3005657","zooniverse_id":"ASC0000gfs","location":{"standard":"http://zooniverse-static.s3.amazonaws.com/www.sciencegossip.org/subjects/standard/54f43ae9efc50104c3005657.jpg","thumb":"http://zooniverse-static.s3.amazonaws.com/www.sciencegossip.org/subjects/thumb/54f43ae9efc50104c3005657.jpg"}}],"tutorial":false,"updated_at":"2015-03-08T21:48:23.457Z","user_id":"53b148fc4e041a5e2e000003","user_name":"Cerian","workflow_id":"54f42c32b35d2e06bd000002"},{"annotations":[{"key":"illustrations","value":"yes"},{"key":"illustration","value":{"0":{"left":"351.827","top":"167.571","width":"395.25","height":"310.231","value":"drawing","frame":"0","parts":{"0":{"x":"580.54","y":"341.662","value":"species","frame":"0","subject":{"common":"Fern Owl","scientific":"Caprimulgus europaeus"}}},"details":{"keywords":"Bird"}}}},{"key":"parts","value":{"0":{"x":"580.54","y":"341.662","value":"species","frame":"0","subject":{"common":"Fern Owl","scientific":"Caprimulgus europaeus"}}}},{"key":"details","value":{"keywords":"Bird"}},{"key":"review","value":""},{"started_at":"Sun, 08 Mar 2015 22:42:58 GMT","finished_at":"Sun, 08 Mar 2015 22:44:35 GMT"},{"user_agent":"Mozilla/5.0 (Windows NT 6.1) AppleWebKit/537.36 (KHTML, like Gecko) Chrome/40.0.2214.115 Safari/537.36"},{"workflow":"untitled_workflow"}],"created_at":"2015-03-08T22:44:30.000Z","id":"54fcd0ce8f165b4b3f005964","project_id":"54f42c0ab35d2e06bd000001","subject_id":"54f43ae9efc50104c3005657","subject_ids":["54f43ae9efc50104c3005657"],"subjects":[{"id":"54f43ae9efc50104c3005657","zooniverse_id":"ASC0000gfs","location":{"standard":"http://zooniverse-static.s3.amazonaws.com/www.sciencegossip.org/subjects/standard/54f43ae9efc50104c3005657.jpg","thumb":"http://zooniverse-static.s3.amazonaws.com/www.sciencegossip.org/subjects/thumb/54f43ae9efc50104c3005657.jpg"}}],"tutorial":false,"updated_at":"2015-03-08T22:44:30.190Z","user_id":"54d5250f832cec457a0001b9","user_name":"tempo_lady","workflow_id":"54f42c32b35d2e06bd000002"},{"annotations":[{"key":"illustrations","value":"skip"},{"started_at":"Wed, 11 Mar 2015 16:34:37 GMT","finished_at":"Wed, 11 Mar 2015 16:35:05 GMT"},{"user_agent":"Mozilla/5.0 (Windows NT 6.0) AppleWebKit/537.36 (KHTML, like Gecko) Chrome/40.0.2214.115 Safari/537.36"},{"workflow":"untitled_workflow"}],"created_at":"2015-03-11T16:35:12.000Z","id":"55006ec00890a94d3c0005bd","project_id":"54f42c0ab35d2e06bd000001","subject_id":"54f43ae9efc50104c3005657","subject_ids":["54f43ae9efc50104c3005657"],"subjects":[{"id":"54f43ae9efc50104c3005657","zooniverse_id":"ASC0000gfs","location":{"standard":"http://zooniverse-static.s3.amazonaws.com/www.sciencegossip.org/subjects/standard/54f43ae9efc50104c3005657.jpg","thumb":"http://zooniverse-static.s3.amazonaws.com/www.sciencegossip.org/subjects/thumb/54f43ae9efc50104c3005657.jpg"}}],"tutorial":false,"updated_at":"2015-03-11T16:35:10.903Z","user_id":"51a3a272a507e82f16000062","user_name":"StrongMay","workflow_id":"54f42c32b35d2e06bd000002"},{"annotations":[{"key":"illustrations","value":"skip"},{"started_at":"Wed, 11 Mar 2015 21:44:49 GMT","finished_at":"Wed, 11 Mar 2015 21:44:57 GMT"},{"user_agent":"Mozilla/5.0 (Windows NT 6.3; WOW64; rv:36.0) Gecko/20100101 Firefox/36.0"},{"workflow":"untitled_workflow"}],"created_at":"2015-03-11T21:44:55.000Z","id":"5500b75770372006f4000b04","project_id":"54f42c0ab35d2e06bd000001","subject_id":"54f43ae9efc50104c3005657","subject_ids":["54f43ae9efc50104c3005657"],"subjects":[{"id":"54f43ae9efc50104c3005657","zooniverse_id":"ASC0000gfs","location":{"standard":"http://zooniverse-static.s3.amazonaws.com/www.sciencegossip.org/subjects/standard/54f43ae9efc50104c3005657.jpg","thumb":"http://zooniverse-static.s3.amazonaws.com/www.sciencegossip.org/subjects/thumb/54f43ae9efc50104c3005657.jpg"}}],"tutorial":false,"updated_at":"2015-03-11T21:44:52.167Z","user_id":"51c2059b501e7e0aba000029","user_name":"annedonnelly","workflow_id":"54f42c32b35d2e06bd000002"},{"annotations":[{"key":"illustrations","value":"yes"},{"key":"illustration","value":{"0":{"left":"348.94","top":"144.646","width":"403.538","height":"333.713","value":"drawing","frame":"0","parts":{"0":{"x":"537.583","y":"295.246","value":"species","frame":"0","subject":{"common":"Fern Owl","scientific":"Caprimulgus europeus"}}},"details":{"keywords":"bird;"}}}},{"key":"parts","value":{"0":{"x":"537.583","y":"295.246","value":"species","frame":"0","subject":{"common":"Fern Owl","scientific":"Caprimulgus europeus"}}}},{"key":"details","value":{"keywords":"bird;"}},{"key":"review","value":""},{"started_at":"Thu, 12 Mar 2015 08:04:39 GMT","finished_at":"Thu, 12 Mar 2015 08:14:04 GMT"},{"user_agent":"Mozilla/5.0 (Windows NT 5.1; rv:36.0) Gecko/20100101 Firefox/36.0"},{"workflow":"untitled_workflow"}],"created_at":"2015-03-12T08:14:00.000Z","id":"55014ac8703720141700027a","project_id":"54f42c0ab35d2e06bd000001","subject_id":"54f43ae9efc50104c3005657","subject_ids":["54f43ae9efc50104c3005657"],"subjects":[{"id":"54f43ae9efc50104c3005657","zooniverse_id":"ASC0000gfs","location":{"standard":"http://zooniverse-static.s3.amazonaws.com/www.sciencegossip.org/subjects/standard/54f43ae9efc50104c3005657.jpg","thumb":"http://zooniverse-static.s3.amazonaws.com/www.sciencegossip.org/subjects/thumb/54f43ae9efc50104c3005657.jpg"}}],"tutorial":false,"updated_at":"2015-03-12T08:14:02.867Z","user_id":"52ebeffaf11e041945001308","user_name":"mcantunez","workflow_id":"54f42c32b35d2e06bd000002"},{"annotations":[{"key":"illustrations","value":"yes"},{"key":"illustration","value":{"0":{"left":"309.792","top":"134.768","width":"499.518","height":"361.346","value":"drawing","frame":"0","details":{"keywords":"bird"}}}},{"key":"parts"},{"key":"details","value":{"keywords":"bird"}},{"key":"review","value":""},{"started_at":"Fri, 13 Mar 2015 11:38:40 GMT","finished_at":"Fri, 13 Mar 2015 11:39:00 GMT"},{"user_agent":"Mozilla/5.0 (Windows NT 6.1; WOW64; rv:36.0) Gecko/20100101 Firefox/36.0"},{"workflow":"untitled_workflow"}],"created_at":"2015-03-13T11:39:01.000Z","id":"5502cc550890a957a800000e","project_id":"54f42c0ab35d2e06bd000001","subject_id":"54f43ae9efc50104c3005657","subject_ids":["54f43ae9efc50104c3005657"],"subjects":[{"id":"54f43ae9efc50104c3005657","zooniverse_id":"ASC0000gfs","location":{"standard":"http://zooniverse-static.s3.amazonaws.com/www.sciencegossip.org/subjects/standard/54f43ae9efc50104c3005657.jpg","thumb":"http://zooniverse-static.s3.amazonaws.com/www.sciencegossip.org/subjects/thumb/54f43ae9efc50104c3005657.jpg"}}],"tutorial":false,"updated_at":"2015-03-13T11:38:57.553Z","user_id":"50f1c943d89f274921000026","user_name":"nilium","workflow_id":"54f42c32b35d2e06bd000002"},{"annotations":[{"key":"illustrations","value":"yes"},{"key":"illustration","value":{"0":{"left":"345.069","top":"148.238","width":"405.566","height":"333.719","value":"drawing","frame":"0","parts":{"0":{"x":"454.221","y":"380.358","value":"species","frame":"0","subject":{"common":"Fern Owl","scientific":"Caprimidgus europaeus"}},"1":{"x":"434.878","y":"256.008","value":"contributor","frame":"0","name":{"name":"Bewick"},"role":{"role":"illustrator"}}},"details":{"keywords":"bird,drawing;foot;Fern Owl;nightjar;mouth bristles;"}}}},{"key":"parts","value":{"0":{"x":"454.221","y":"380.358","value":"species","frame":"0","subject":{"common":"Fern Owl","scientific":"Caprimidgus europaeus"}},"1":{"x":"434.878","y":"256.008","value":"contributor","frame":"0","name":{"name":"Bewick"},"role":{"role":"illustrator"}}}},{"key":"details","value":{"keywords":"bird,drawing;foot;Fern Owl;nightjar;mouth bristles;"}},{"key":"review","value":""},{"started_at":"Sat, 14 Mar 2015 18:18:15 GMT","finished_at":"Sat, 14 Mar 2015 18:23:08 GMT"},{"user_agent":"Mozilla/5.0 (Macintosh; Intel Mac OS X 10_9_5) AppleWebKit/600.3.18 (KHTML, like Gecko) Version/7.1.3 Safari/537.85.12"},{"workflow":"untitled_workflow"}],"created_at":"2015-03-14T18:23:04.000Z","id":"55047c88703720345800071f","project_id":"54f42c0ab35d2e06bd000001","subject_id":"54f43ae9efc50104c3005657","subject_ids":["54f43ae9efc50104c3005657"],"subjects":[{"id":"54f43ae9efc50104c3005657","zooniverse_id":"ASC0000gfs","location":{"standard":"http://zooniverse-static.s3.amazonaws.com/www.sciencegossip.org/subjects/standard/54f43ae9efc50104c3005657.jpg","thumb":"http://zooniverse-static.s3.amazonaws.com/www.sciencegossip.org/subjects/thumb/54f43ae9efc50104c3005657.jpg"}}],"tutorial":false,"updated_at":"2015-03-14T18:23:04.698Z","user_id":"50f1aa9d1659d337c1000007","user_name":"Aerialeagleye","workflow_id":"54f42c32b35d2e06bd000002"},{"annotations":[{"key":"illustrations","value":"yes"},{"key":"illustration","value":{"0":{"left":"345.969","top":"145.015","width":"408.328","height":"332.332","value":"drawing","frame":"0","parts":{"0":{"x":"503.479","y":"302.523","value":"species","frame":"0","subject":{"common":"Fern Owl","scientific":"Caprimidgus europaeus"}}},"details":{"keywords":"bird; structure of foot; tarsus;"}}}},{"key":"parts","value":{"0":{"x":"503.479","y":"302.523","value":"species","frame":"0","subject":{"common":"Fern Owl","scientific":"Caprimidgus europaeus"}}}},{"key":"details","value":{"keywords":"bird; structure of foot; tarsus;"}},{"key":"review","value":""},{"started_at":"Sun, 15 Mar 2015 22:21:50 GMT","finished_at":"Sun, 15 Mar 2015 22:24:32 GMT"},{"user_agent":"Mozilla/5.0 (Windows NT 5.1; rv:36.0) Gecko/20100101 Firefox/36.0"},{"workflow":"untitled_workflow"}],"created_at":"2015-03-15T22:24:25.000Z","id":"550606997037202ab800098b","project_id":"54f42c0ab35d2e06bd000001","subject_id":"54f43ae9efc50104c3005657","subject_ids":["54f43ae9efc50104c3005657"],"subjects":[{"id":"54f43ae9efc50104c3005657","zooniverse_id":"ASC0000gfs","location":{"standard":"http://zooniverse-static.s3.amazonaws.com/www.sciencegossip.org/subjects/standard/54f43ae9efc50104c3005657.jpg","thumb":"http://zooniverse-static.s3.amazonaws.com/www.sciencegossip.org/subjects/thumb/54f43ae9efc50104c3005657.jpg"}}],"tutorial":false,"updated_at":"2015-03-15T22:24:31.566Z","user_id":"51840777de59d924d6000003","user_name":"mudlark","workflow_id":"54f42c32b35d2e06bd000002"},{"annotations":[{"key":"illustrations","value":"yes"},{"key":"illustration","value":{"0":{"left":"340.487","top":"137.184","width":"417.447","height":"351.036","value":"drawing","frame":"0","details":{"keywords":"ornithology; foot; anatomy; tarsus; toe; claw"}}}},{"key":"parts","value":{"0":{"x":"629.348","y":"43.231","value":"species","frame":"0","subject":{"common":"Fern Owl","scientific":"Caprimulgus europaeus"}}}},{"key":"details","value":{"keywords":"ornithology; foot; anatomy; tarsus; toe; claw"}},{"key":"review","value":""},{"started_at":"Sat, 21 Mar 2015 01:49:20 GMT","finished_at":"Sat, 21 Mar 2015 01:56:14 GMT"},{"user_agent":"Mozilla/5.0 (iPad; CPU OS 8_2 like Mac OS X) AppleWebKit/600.1.4 (KHTML, like Gecko) CriOS/41.0.2272.56 Mobile/12D508 Safari/600.1.4 (000358)"},{"workflow":"untitled_workflow"}],"created_at":"2015-03-21T01:56:17.000Z","id":"550ccfc10513701842000343","project_id":"54f42c0ab35d2e06bd000001","subject_id":"54f43ae9efc50104c3005657","subject_ids":["54f43ae9efc50104c3005657"],"subjects":[{"id":"54f43ae9efc50104c3005657","zooniverse_id":"ASC0000gfs","location":{"standard":"http://zooniverse-static.s3.amazonaws.com/www.sciencegossip.org/subjects/standard/54f43ae9efc50104c3005657.jpg","thumb":"http://zooniverse-static.s3.amazonaws.com/www.sciencegossip.org/subjects/thumb/54f43ae9efc50104c3005657.jpg"}}],"tutorial":false,"updated_at":"2015-03-21T01:56:16.289Z","user_id":"54a6fb77bb7b561453000034","user_name":"Shiphrah","workflow_id":"54f42c32b35d2e06bd000002"}]
