[{"annotations":[{"key":"illustrations","value":"no"},{"started_at":"Fri, 18 Mar 2016 19:55:38 GMT","finished_at":"Fri, 18 Mar 2016 19:55:41 GMT"},{"user_agent":"Mozilla/5.0 (Windows NT 6.3; WOW64; rv:44.0) Gecko/20100101 Firefox/44.0"},{"workflow":"untitled_workflow"}],"created_at":"2016-03-18T19:56:16.000Z","id":"56ec5d607b36ef618900052d","project_id":"54f42c0ab35d2e06bd000001","subject_id":"56c48b4dbcdc20004200a17d","subject_ids":["56c48b4dbcdc20004200a17d"],"subjects":[{"id":"56c48b4dbcdc20004200a17d","zooniverse_id":"ASC0003yuh","location":{"standard":"http://zooniverse-static.s3.amazonaws.com/www.sciencegossip.org/subjects/standard/56c48b4dbcdc20004200a17d.jpg","thumb":"http://zooniverse-static.s3.amazonaws.com/www.sciencegossip.org/subjects/thumb/56c48b4dbcdc20004200a17d.jpg"}}],"tutorial":false,"updated_at":"2016-03-18T19:56:16.455Z","user_id":"5041cb2bba40af4d53000034","user_name":"elizabeth_s","workflow_id":"54f42c32b35d2e06bd000002"},{"annotations":[{"key":"illustrations","value":"skip"},{"started_at":"Tue, 03 May 2016 22:32:05 GMT","finished_at":"Tue, 03 May 2016 22:32:10 GMT"},{"user_agent":"Mozilla/5.0 (Windows NT 6.1; WOW64) AppleWebKit/537.36 (KHTML, like Gecko) Chrome/50.0.2661.94 Safari/537.36"},{"workflow":"untitled_workflow"}],"created_at":"2016-05-03T22:32:10.000Z","id":"572926eaf96efa00ae001e72","project_id":"54f42c0ab35d2e06bd000001","subject_id":"56c48b4dbcdc20004200a17d","subject_ids":["56c48b4dbcdc20004200a17d"],"subjects":[{"id":"56c48b4dbcdc20004200a17d","zooniverse_id":"ASC0003yuh","location":{"standard":"http://zooniverse-static.s3.amazonaws.com/www.sciencegossip.org/subjects/standard/56c48b4dbcdc20004200a17d.jpg","thumb":"http://zooniverse-static.s3.amazonaws.com/www.sciencegossip.org/subjects/thumb/56c48b4dbcdc20004200a17d.jpg"}}],"tutorial":false,"updated_at":"2016-05-03T22:32:10.525Z","user_id":"5584930c2a19956404000bc4","user_name":"OneTwoTree","workflow_id":"54f42c32b35d2e06bd000002"},{"annotations":[{"key":"illustrations","value":"yes"},{"key":"illustration","value":{"0":{"left":"81.458","top":"243.971","width":"319.408","height":"860.77","value":"drawing","frame":"0","parts":{"0":{"x":"146.867","y":"1006.608","value":"inscription","frame":"0","inscription":{"text":"a"}},"1":{"x":"100.942","y":"1014.958","value":"inscription","frame":"0","inscription":{"text":"Trias."}},"2":{"x":"100.942","y":"797.857","value":"inscription","frame":"0","inscription":{"text":"Lias."}},"3":{"x":"149.65","y":"856.308","value":"inscription","frame":"0","inscription":{"text":"b"}},"4":{"x":"148.258","y":"721.315","value":"inscription","frame":"0","inscription":{"text":"c"}},"5":{"x":"148.258","y":"658.69","value":"inscription","frame":"0","inscription":{"text":"d"}},"6":{"x":"148.258","y":"598.848","value":"inscription","frame":"0","inscription":{"text":"e"}},"7":{"x":"153.825","y":"483.339","value":"inscription","frame":"0","inscription":{"text":"f"}},"8":{"x":"156.608","y":"324.688","value":"inscription","frame":"0","inscription":{"text":"g"}},"9":{"x":"93.983","y":"416.539","value":"inscription","frame":"0","inscription":{"text":"Bath Oolite."}}},"details":{"keywords":"statigraphy;cleveland;section;"}}}},{"key":"parts","value":{"0":{"x":"146.867","y":"1006.608","value":"inscription","frame":"0","inscription":{"text":"a"}},"1":{"x":"100.942","y":"1014.958","value":"inscription","frame":"0","inscription":{"text":"Trias."}},"2":{"x":"100.942","y":"797.857","value":"inscription","frame":"0","inscription":{"text":"Lias."}},"3":{"x":"149.65","y":"856.308","value":"inscription","frame":"0","inscription":{"text":"b"}},"4":{"x":"148.258","y":"721.315","value":"inscription","frame":"0","inscription":{"text":"c"}},"5":{"x":"148.258","y":"658.69","value":"inscription","frame":"0","inscription":{"text":"d"}},"6":{"x":"148.258","y":"598.848","value":"inscription","frame":"0","inscription":{"text":"e"}},"7":{"x":"153.825","y":"483.339","value":"inscription","frame":"0","inscription":{"text":"f"}},"8":{"x":"156.608","y":"324.688","value":"inscription","frame":"0","inscription":{"text":"g"}},"9":{"x":"93.983","y":"416.539","value":"inscription","frame":"0","inscription":{"text":"Bath Oolite."}}}},{"key":"details","value":{"keywords":"statigraphy;cleveland;section;"}},{"key":"review","value":""},{"started_at":"Sat, 03 Sep 2016 21:03:34 GMT","finished_at":"Sat, 03 Sep 2016 21:08:28 GMT"},{"user_agent":"Mozilla/5.0 (Macintosh; Intel Mac OS X 10.8; rv:43.0) Gecko/20100101 Firefox/43.0 SeaMonkey/2.40"},{"workflow":"untitled_workflow"}],"created_at":"2016-09-03T21:08:28.000Z","id":"57cb3bcc09a94f5927000cd7","project_id":"54f42c0ab35d2e06bd000001","subject_id":"56c48b4dbcdc20004200a17d","subject_ids":["56c48b4dbcdc20004200a17d"],"subjects":[{"id":"56c48b4dbcdc20004200a17d","zooniverse_id":"ASC0003yuh","location":{"standard":"http://zooniverse-static.s3.amazonaws.com/www.sciencegossip.org/subjects/standard/56c48b4dbcdc20004200a17d.jpg","thumb":"http://zooniverse-static.s3.amazonaws.com/www.sciencegossip.org/subjects/thumb/56c48b4dbcdc20004200a17d.jpg"}}],"tutorial":false,"updated_at":"2016-09-03T21:08:28.973Z","user_id":"54f9e5bacf0441308000031d","user_name":"JANEJ","workflow_id":"54f42c32b35d2e06bd000002"},{"annotations":[{"key":"illustrations","value":"yes"},{"key":"illustration","value":{"0":{"left":"91.089","top":"255.561","width":"315.236","height":"855.207","value":"drawing","frame":"0","details":{"keywords":""}}}},{"key":"parts"},{"key":"details","value":{"keywords":""}},{"key":"review","value":""},{"started_at":"Mon, 20 Feb 2017 03:16:15 GMT","finished_at":"Mon, 20 Feb 2017 03:16:21 GMT"},{"user_agent":"Mozilla/5.0 (Windows NT 10.0; Win64; x64) AppleWebKit/537.36 (KHTML, like Gecko) Chrome/56.0.2924.87 Safari/537.36"},{"workflow":"untitled_workflow"}],"created_at":"2017-02-20T03:16:22.000Z","id":"58aa5f867d25c70079000cd2","project_id":"54f42c0ab35d2e06bd000001","subject_id":"56c48b4dbcdc20004200a17d","subject_ids":["56c48b4dbcdc20004200a17d"],"subjects":[{"id":"56c48b4dbcdc20004200a17d","zooniverse_id":"ASC0003yuh","location":{"standard":"http://zooniverse-static.s3.amazonaws.com/www.sciencegossip.org/subjects/standard/56c48b4dbcdc20004200a17d.jpg","thumb":"http://zooniverse-static.s3.amazonaws.com/www.sciencegossip.org/subjects/thumb/56c48b4dbcdc20004200a17d.jpg"}}],"tutorial":false,"updated_at":"2017-02-20T03:16:22.138Z","user_id":"58a6593e7d25c76b25000731","user_name":"sskhera","workflow_id":"54f42c32b35d2e06bd000002"},{"annotations":[{"key":"illustrations","value":"yes"},{"key":"illustration","value":{"0":{"left":"102.915","top":"245.836","width":"298.534","height":"857.986","value":"drawing","frame":"0","details":{"keywords":"Division of Mesozoic Series. "}}}},{"key":"parts"},{"key":"details","value":{"keywords":"Division of Mesozoic Series. "}},{"key":"review","value":""},{"started_at":"Wed, 22 Feb 2017 22:29:20 GMT","finished_at":"Wed, 22 Feb 2017 22:31:25 GMT"},{"user_agent":"Mozilla/5.0 (Windows NT 6.3; Win64; x64) AppleWebKit/537.36 (KHTML, like Gecko) Chrome/56.0.2924.87 Safari/537.36"},{"workflow":"untitled_workflow"}],"created_at":"2017-02-22T22:30:53.000Z","id":"58ae111d7d25c7245a000121","project_id":"54f42c0ab35d2e06bd000001","subject_id":"56c48b4dbcdc20004200a17d","subject_ids":["56c48b4dbcdc20004200a17d"],"subjects":[{"id":"56c48b4dbcdc20004200a17d","zooniverse_id":"ASC0003yuh","location":{"standard":"http://zooniverse-static.s3.amazonaws.com/www.sciencegossip.org/subjects/standard/56c48b4dbcdc20004200a17d.jpg","thumb":"http://zooniverse-static.s3.amazonaws.com/www.sciencegossip.org/subjects/thumb/56c48b4dbcdc20004200a17d.jpg"}}],"tutorial":false,"updated_at":"2017-02-22T22:30:53.803Z","user_id":null,"workflow_id":"54f42c32b35d2e06bd000002"},{"annotations":[{"key":"illustrations","value":"skip"},{"started_at":"Thu, 23 Feb 2017 16:00:51 GMT","finished_at":"Thu, 23 Feb 2017 16:01:02 GMT"},{"user_agent":"Mozilla/5.0 (Windows NT 6.1; WOW64) AppleWebKit/537.36 (KHTML, like Gecko) Chrome/56.0.2924.87 Safari/537.36"},{"workflow":"untitled_workflow"}],"created_at":"2017-02-23T16:18:51.000Z","id":"58af0b6b7d25c75c75000323","project_id":"54f42c0ab35d2e06bd000001","subject_id":"56c48b4dbcdc20004200a17d","subject_ids":["56c48b4dbcdc20004200a17d"],"subjects":[{"id":"56c48b4dbcdc20004200a17d","zooniverse_id":"ASC0003yuh","location":{"standard":"http://zooniverse-static.s3.amazonaws.com/www.sciencegossip.org/subjects/standard/56c48b4dbcdc20004200a17d.jpg","thumb":"http://zooniverse-static.s3.amazonaws.com/www.sciencegossip.org/subjects/thumb/56c48b4dbcdc20004200a17d.jpg"}}],"tutorial":false,"updated_at":"2017-02-23T16:18:51.459Z","user_id":"553c4f79fe86d94225000204","user_name":"beablauth","workflow_id":"54f42c32b35d2e06bd000002"},{"annotations":[{"key":"illustrations","value":"yes"},{"key":"illustration","value":{"0":{"left":"58.903","top":"259.753","width":"355.592","height":"842.678","value":"drawing","frame":"0","parts":{"0":{"x":"117.354","y":"460.154","value":"inscription","frame":"0","inscription":{"text":"Bath Oolite"}},"1":{"x":"117.354","y":"823.38","value":"inscription","frame":"0","inscription":{"text":"Lias"}},"2":{"x":"124.312","y":"1059.964","value":"inscription","frame":"0","inscription":{"text":"Tiras"}}},"details":{"keywords":""}}}},{"key":"parts","value":{"0":{"x":"117.354","y":"460.154","value":"inscription","frame":"0","inscription":{"text":"Bath Oolite"}},"1":{"x":"117.354","y":"823.38","value":"inscription","frame":"0","inscription":{"text":"Lias"}},"2":{"x":"124.312","y":"1059.964","value":"inscription","frame":"0","inscription":{"text":"Tiras"}}}},{"key":"details","value":{"keywords":""}},{"key":"review","value":""},{"started_at":"Sun, 26 Mar 2017 21:56:45 GMT","finished_at":"Sun, 26 Mar 2017 21:57:23 GMT"},{"user_agent":"Mozilla/5.0 (Macintosh; Intel Mac OS X 10_12) AppleWebKit/602.1.50 (KHTML, like Gecko) Version/10.0 Safari/602.1.50"},{"workflow":"untitled_workflow"}],"created_at":"2017-03-26T21:57:24.000Z","id":"58d8394454aedf0086000d8c","project_id":"54f42c0ab35d2e06bd000001","subject_id":"56c48b4dbcdc20004200a17d","subject_ids":["56c48b4dbcdc20004200a17d"],"subjects":[{"id":"56c48b4dbcdc20004200a17d","zooniverse_id":"ASC0003yuh","location":{"standard":"http://zooniverse-static.s3.amazonaws.com/www.sciencegossip.org/subjects/standard/56c48b4dbcdc20004200a17d.jpg","thumb":"http://zooniverse-static.s3.amazonaws.com/www.sciencegossip.org/subjects/thumb/56c48b4dbcdc20004200a17d.jpg"}}],"tutorial":false,"updated_at":"2017-03-26T21:57:24.172Z","user_id":null,"workflow_id":"54f42c32b35d2e06bd000002"},{"annotations":[{"key":"illustrations","value":"yes"},{"key":"illustration","value":{"0":{"left":"74.755","top":"261.145","width":"309.667","height":"849.636","value":"drawing","frame":"0","details":{"keywords":"Mesozoic; limestone; shales; sandstones; lias; Exeter;"}}}},{"key":"parts"},{"key":"details","value":{"keywords":"Mesozoic; limestone; shales; sandstones; lias; Exeter;"}},{"key":"review","value":""},{"started_at":"Mon, 27 Mar 2017 19:47:34 GMT","finished_at":"Mon, 27 Mar 2017 19:49:24 GMT"},{"user_agent":"Mozilla/5.0 (Windows NT 10.0; WOW64) AppleWebKit/537.36 (KHTML, like Gecko) Chrome/56.0.2924.87 Safari/537.36"},{"workflow":"untitled_workflow"}],"created_at":"2017-03-27T19:48:49.000Z","id":"58d96ca1ea8d2b00760007b2","project_id":"54f42c0ab35d2e06bd000001","subject_id":"56c48b4dbcdc20004200a17d","subject_ids":["56c48b4dbcdc20004200a17d"],"subjects":[{"id":"56c48b4dbcdc20004200a17d","zooniverse_id":"ASC0003yuh","location":{"standard":"http://zooniverse-static.s3.amazonaws.com/www.sciencegossip.org/subjects/standard/56c48b4dbcdc20004200a17d.jpg","thumb":"http://zooniverse-static.s3.amazonaws.com/www.sciencegossip.org/subjects/thumb/56c48b4dbcdc20004200a17d.jpg"}}],"tutorial":false,"updated_at":"2017-03-27T19:48:49.578Z","user_id":null,"workflow_id":"54f42c32b35d2e06bd000002"}]
